pyproject.toml
earthflow/__init__.py
earthflow.egg-info/PKG-INFO
earthflow.egg-info/SOURCES.txt
earthflow.egg-info/dependency_links.txt
earthflow.egg-info/top_level.txt