Metadata-Version: 2.1
Name: earthflow
Version: 0.0.0
Summary: coming soon
Author-email: Tennessee Leeuwenburg <tennessee.leeuwenburg@bom.gov.au>
